gitwsrepo/__init__.py
gitwsrepo/__main__.py
gitwsrepo/_cli/__init__.py
gitwsrepo/_cli/common.py
gitwsrepo/_cli/logging.py
gitwsrepo/repomanifestformat.py
git_ws_repo-0.2.0.dist-info/COPYING
git_ws_repo-0.2.0.dist-info/COPYING.LESSER
git_ws_repo-0.2.0.dist-info/METADATA
git_ws_repo-0.2.0.dist-info/WHEEL
git_ws_repo-0.2.0.dist-info/entry_points.txt
git_ws_repo-0.2.0.dist-info/RECORD
