Metadata-Version: 2.1
Name: git-ws-repo
Version: 0.2.0
Summary: Google's git-repo replacement powered by git-ws
License: LGPL-3.0-or-later
Author: c0fec0de
Author-email: c0fec0de@gmail.com
Requires-Python: >=3.8.2,<4.0.0
Classifier: License :: OSI Approved :: GNU Lesser General Public License v3 or later (LGPLv3+)
Classifier: Operating System :: OS Independent
Classifier: Programming Language :: Python :: 3
Classifier: Programming Language :: Python :: 3.9
Classifier: Programming Language :: Python :: 3.10
Classifier: Programming Language :: Python :: 3.11
Classifier: Programming Language :: Python :: 3.12
Requires-Dist: defusedxml (>=0.7.1,<0.8.0)
Requires-Dist: git-ws (>=2.0.0,<3.0.0)
